lazyprint/__init__.py
lazyprint-0.0.0.dist-info/METADATA
lazyprint-0.0.0.dist-info/WHEEL
lazyprint-0.0.0.dist-info/top_level.txt
lazyprint-0.0.0.dist-info/RECORD
