Metadata-Version: 2.1
Name: lazyprint
Version: 0.0.0
Summary: Coming soon
Author-email: Matt Mitchell <matt.mitchell97@hotmail.com>
